mb_utils/src/__init__.py
mb_utils/src/deprecated.py
mb_utils/src/extra.py
mb_utils/src/logging.py
mb_utils/src/path_checker.py
mb_utils/src/retry_decorator.py
mb_utils/src/s3.py
mb_utils/src/terminal.py
mb_utils/src/verify_image.py
mb_utils/src/version.py
mb_utils-1.0.202307061425.dist-info/METADATA
mb_utils-1.0.202307061425.dist-info/WHEEL
mb_utils-1.0.202307061425.dist-info/top_level.txt
mb_utils-1.0.202307061425.dist-info/RECORD
