Metadata-Version: 2.1
Name: mb-utils
Version: 1.0.202307061425
Summary: Basic logger and utils package
Author: ['Malav Bateriwala']
Requires-Python: >=3.8
Requires-Dist: numpy
Requires-Dist: pandas
Requires-Dist: colorama
Requires-Dist: fastprogress
Requires-Dist: boto3
